Workbook
Name aporte: APP!$D$14
Name qtd_anos: APP!$D$15
Name rendimento_carteira: APP!$D$10
Name salario: APP!$D$9
Name sugestao_invest: APP!$D$11
Name taxa_invest: APP!$D$16

Sheet APP
B8: CONFIGURAÇÕES
B9: Salário | D9: 5000
B10: Rendimento Carteira | D10: 0.01
B11: Sugestão de Investimento | D11: =salario*30% -> 1500
B13: INVESTIMENTO MENSAL
B14: Quanto investir por mês? | D14: 500
B15: Por Quanto Anos? | D15: 5
B16: Taxa de rendimento mesal? | D16: 0.01079
B17: Qual o patrimônio total? | D17: =FV(taxa_invest,qtd_anos*12,aporte*-1) -> 41888.457
B18: Quais dividendos mensais? | D18: =D17*rendimento_carteira -> 418.88457
B20: Cenários | D20: Dividendos
A21: 2 | B21: Quanto em 2 Anos? | C21: =FV($D$16,A21*12,$D$14*-1) -> 13613.814 | D21: =C21*rendimento_carteira -> 136.13814
A22: 5 | B22: Quanto em 5 Anos? | C22: =FV($D$16,A22*12,$D$14*-1) -> 41888.457 | D22: =C22*rendimento_carteira -> 418.88457
A23: 10 | B23: Quanto em 10 Anos? | C23: =FV($D$16,A23*12,$D$14*-1) -> 121642.11 | D23: =C23*rendimento_carteira -> 1216.4211
A24: 20 | B24: Quanto em 20 Anos? | C24: =FV($D$16,A24*12,$D$14*-1) -> 562599.2 | D24: =C24*rendimento_carteira -> 5625.992
A25: 30 | B25: Quanto em 30 Anos? | C25: =FV($D$16,A25*12,$D$14*-1) -> 2161084.8 | D25: =C25*rendimento_carteira -> 21610.848
B28: SELECIONE UM PERFIL DE INVESTIDOR | D28: Conservador
B29: VALOR A SER INVESTIDO POR MÊS | D29: =aporte -> 500
B31: TIPO DE FII | C31: Percentual Sugerido | D31: Valores
B32: PAPEL | C32: =VLOOKUP($D$28&"-"&$B32,tb_PERFIL_INVEST!A:D,4,FALSE) -> 0.3 | D32: =C32*$D$29 -> 150
B33: TIJOLO | C33: =VLOOKUP($D$28&"-"&$B33,tb_PERFIL_INVEST!A:D,4,FALSE) -> 0.5 | D33: =C33*$D$29 -> 250
B34: HIBRIDOS | C34: =VLOOKUP($D$28&"-"&$B34,tb_PERFIL_INVEST!A:D,4,FALSE) -> 0.1 | D34: =C34*$D$29 -> 50
B35: FOFs | C35: =VLOOKUP($D$28&"-"&$B35,tb_PERFIL_INVEST!A:D,4,FALSE) -> 0.1 | D35: =C35*$D$29 -> 50
B36: DESENVOLVIMENTO | C36: =VLOOKUP($D$28&"-"&$B36,tb_PERFIL_INVEST!A:D,4,FALSE) -> 0 | D36: =C36*$D$29 -> 0
B37: HOTELATIAS | C37: =VLOOKUP($D$28&"-"&$B37,tb_PERFIL_INVEST!A:D,4,FALSE) -> 0 | D37: =C37*$D$29 -> 0
D38: =SUM(D32:D37) -> 500

Sheet tb_PERFIL_INVEST
A2: CHAVE | B2: PERFIL | C2: TIPO FII | D2: %
A3: =B3&"-"&C3 -> Conservador-PAPEL | B3: Conservador | C3: PAPEL | D3: 0.3
A4: =B4&"-"&C4 -> Conservador-TIJOLO | B4: Conservador | C4: TIJOLO | D4: 0.5
A5: =B5&"-"&C5 -> Conservador-HIBRIDOS | B5: Conservador | C5: HIBRIDOS | D5: 0.1
A6: =B6&"-"&C6 -> Conservador-FOFs | B6: Conservador | C6: FOFs | D6: 0.1
A7: =B7&"-"&C7 -> Conservador-DESENVOLVIMENTO | B7: Conservador | C7: DESENVOLVIMENTO | D7: 0
A8: =B8&"-"&C8 -> Conservador-HOTELATIAS | B8: Conservador | C8: HOTELATIAS | D8: 0
A9: =B9&"-"&C9 -> Moderado-PAPEL | B9: Moderado | C9: PAPEL | D9: 0.32
A10: =B10&"-"&C10 -> Moderado-TIJOLO | B10: Moderado | C10: TIJOLO | D10: 0.35
A11: =B11&"-"&C11 -> Moderado-HIBRIDOS | B11: Moderado | C11: HIBRIDOS | D11: 0.08
A12: =B12&"-"&C12 -> Moderado-FOFs | B12: Moderado | C12: FOFs | D12: 0.05
A13: =B13&"-"&C13 -> Moderado-DESENVOLVIMENTO | B13: Moderado | C13: DESENVOLVIMENTO | D13: 0.1
A14: =B14&"-"&C14 -> Moderado-HOTELATIAS | B14: Moderado | C14: HOTELATIAS | D14: 0.1
... A20: =B20&"-"&C20 -> Agressivo-HOTELATIAS | B20: Agressivo | C20: HOTELATIAS | D20: 0.1
